lsj/__init__.py
lsj/_lsj.cpython-313-x86_64-linux-gnu.so
lsj/_lsj.pyi
lsj_toolkit.libs/libbrotlicommon-24c3c480.so.1.0.9
lsj_toolkit.libs/libbrotlidec-11aaeb4b.so.1.0.9
lsj_toolkit.libs/libcom_err-f13ee7b5.so.2.1
lsj_toolkit.libs/libcrypt-1e9ce68f.so.2.0.0
lsj_toolkit.libs/libcrypto-a07a2e9c.so.3.2.2
lsj_toolkit.libs/libcurl-997f44d6.so.4.7.0
lsj_toolkit.libs/libevent-2-bb9471ec.1.so.7.0.1
lsj_toolkit.libs/libgssapi_krb5-ddb8be02.so.2.2
lsj_toolkit.libs/libidn2-5237fb84.so.0.3.7
lsj_toolkit.libs/libjson-c-eb53328e.so.5.0.0
lsj_toolkit.libs/libk5crypto-af0bccff.so.3.1
lsj_toolkit.libs/libkeyutils-81e5c457.so.1.10
lsj_toolkit.libs/libkrb5-75112af1.so.3.3
lsj_toolkit.libs/libkrb5support-86b10edf.so.0.1
lsj_toolkit.libs/liblber-a3e026a5.so.2.0.200
lsj_toolkit.libs/libldap_r-85173b02.so.2.0.200
lsj_toolkit.libs/libnghttp2-25a83100.so.14.20.1
lsj_toolkit.libs/libpcre2-8-b77f698a.so.0.11.0
lsj_toolkit.libs/libpsl-5e17ba32.so.5.3.3
lsj_toolkit.libs/libsasl2-6b2d3aab.so.3.0.0
lsj_toolkit.libs/libselinux-7b1dc4ca.so.1
lsj_toolkit.libs/libssh-04f53293.so.4.9.4
lsj_toolkit.libs/libssl-6942ff50.so.3.2.2
lsj_toolkit.libs/libunistring-7ed7589d.so.2.1.0
lsj_toolkit-1.0.2.dist-info/METADATA
lsj_toolkit-1.0.2.dist-info/WHEEL
lsj_toolkit-1.0.2.dist-info/top_level.txt
lsj_toolkit-1.0.2.dist-info/RECORD
